visualize.py
RadixAPI-0.0.1.dist-info/METADATA
RadixAPI-0.0.1.dist-info/WHEEL
RadixAPI-0.0.1.dist-info/top_level.txt
RadixAPI-0.0.1.dist-info/RECORD
