Metadata-Version: 2.1
Name: RadixAPI
Version: 0.0.1
Summary: Sampler/Visualizer for small Datasets
Home-page: UNKNOWN
License: UNKNOWN
Platform: UNKNOWN
Requires-Python: >=3.6
Requires-Dist: pandas
Requires-Dist: numpy
Requires-Dist: xlrd
